README.rst
setup.py
fusillade/__init__.py
fusillade.egg-info/PKG-INFO
fusillade.egg-info/SOURCES.txt
fusillade.egg-info/dependency_links.txt
fusillade.egg-info/requires.txt
fusillade.egg-info/top_level.txt