Metadata-Version: 1.1
Name: fusillade
Version: 0.0.1
Summary: Federated User Identity Login & Access Decision Engine
Home-page: https://github.com/humancellatlas/fusillade
Author: Andrey Kislyuk
Author-email: kislyuk@gmail.com
License: MIT License
Platform: MacOS X
Platform: Posix
Classifier: Intended Audience :: Developers
Classifier: License :: OSI Approved :: Apache Software License
Classifier: Operating System :: MacOS :: MacOS X
Classifier: Operating System :: POSIX
Classifier: Programming Language :: Python
Classifier: Programming Language :: Python :: 3.6
Classifier: Topic :: Software Development :: Libraries :: Python Modules
